patch_package_py/__init__.py
patch_package_py/cli.py
patch_package_py/core.py
patch_package_py-0.1.3.dist-info/METADATA
patch_package_py-0.1.3.dist-info/WHEEL
patch_package_py-0.1.3.dist-info/entry_points.txt
patch_package_py-0.1.3.dist-info/RECORD
