Metadata-Version: 2.4
Name: patch-package-py
Version: 0.1.3
Summary: patch 3rd party Python packages
Project-URL: Homepage, https://github.com/nomyfan/patch-package-py
Project-URL: Repository, https://github.com/nomyfan/patch-package-py
Project-URL: Issues, https://github.com/nomyfan/patch-package-py/issues
Author-email: nomyfan <nomyfan@live.com>
License: MIT
Classifier: Development Status :: 3 - Alpha
Classifier: Intended Audience :: Developers
Classifier: License :: OSI Approved :: MIT License
Classifier: Programming Language :: Python :: 3
Classifier: Programming Language :: Python :: 3.9
Classifier: Programming Language :: Python :: 3.10
Classifier: Programming Language :: Python :: 3.11
Classifier: Programming Language :: Python :: 3.12
Requires-Python: >=3.9
